yapss/__init__.py
yapss/py.typed
yapss/_private/__init__.py
yapss/_private/auto.py
yapss/_private/bounds.py
yapss/_private/central_difference.py
yapss/_private/config.py
yapss/_private/finite_difference.py
yapss/_private/guess.py
yapss/_private/input_args.py
yapss/_private/ipopt_options.py
yapss/_private/mesh.py
yapss/_private/nlp.py
yapss/_private/problem.py
yapss/_private/quadrature.py
yapss/_private/solution.py
yapss/_private/solver.py
yapss/_private/structure.py
yapss/_private/types_.py
yapss/_private/user.py
yapss/examples/__init__.py
yapss/examples/brachistochrone.py
yapss/examples/brachistochrone_minimal.py
yapss/examples/delta_iii_ascent.py
yapss/examples/dynamic_soaring.py
yapss/examples/goddard_problem_1_phase.py
yapss/examples/goddard_problem_3_phase.py
yapss/examples/hs071.py
yapss/examples/isoperimetric.py
yapss/examples/minimum_time_to_climb.py
yapss/examples/newton.py
yapss/examples/orbit_raising.py
yapss/examples/rosenbrock.py
yapss/math/__init__.py
yapss/math/functions.py
yapss/math/wrapper.py
yapss-0.1.0.dist-info/METADATA
yapss-0.1.0.dist-info/WHEEL
yapss-0.1.0.dist-info/licenses/LICENSE
yapss-0.1.0.dist-info/RECORD
