Metadata-Version: 2.4
Name: yapss
Version: 0.1.0
Summary: A Python package for solving optimal control problems using pseudospectral methods.
Project-URL: Documentation, https://yapss.readthedocs.io/
Project-URL: Repository, https://github.com/stevenrhall/yapss.git
Project-URL: Issues, https://github.com/stevenrhall/yapss/issues
Project-URL: Changelog, https://github.com/stevenrhall/yapss/blob/main/CHANGELOG.md
Author-email: "Steven R. Hall" <steve@steven-hall.net>
Maintainer-email: "Steven R. Hall" <steve@steven-hall.net>
License-File: LICENSE
Keywords: optimal control,optimization,pseudospectral methods
Classifier: Development Status :: 4 - Beta
Classifier: Intended Audience :: Education
Classifier: Intended Audience :: Science/Research
Classifier: License :: OSI Approved :: MIT License
Classifier: Programming Language :: Python :: 3
Classifier: Programming Language :: Python :: 3 :: Only
Classifier: Programming Language :: Python :: 3.9
Classifier: Programming Language :: Python :: 3.10
Classifier: Programming Language :: Python :: 3.11
Classifier: Programming Language :: Python :: 3.12
Classifier: Programming Language :: Python :: 3.13
Classifier: Topic :: Scientific/Engineering
Requires-Python: >=3.9
Requires-Dist: casadi>=3.6.0
Requires-Dist: matplotlib
Requires-Dist: mpmath
Requires-Dist: mseipopt
Requires-Dist: numpy
Requires-Dist: scipy
Provides-Extra: dev
Requires-Dist: black[jupyter]<25.0.0,>=24.0.0; extra == 'dev'
Requires-Dist: furo; extra == 'dev'
Requires-Dist: hatch; extra == 'dev'
Requires-Dist: isort; extra == 'dev'
Requires-Dist: jupyterlab; extra == 'dev'
Requires-Dist: jupyterlab-code-formatter; extra == 'dev'
Requires-Dist: jupyterlab-spellchecker; extra == 'dev'
Requires-Dist: lxml; extra == 'dev'
Requires-Dist: mypy; extra == 'dev'
Requires-Dist: myst-parser; extra == 'dev'
Requires-Dist: nbsphinx; extra == 'dev'
Requires-Dist: nbwipers; extra == 'dev'
Requires-Dist: numpydoc; extra == 'dev'
Requires-Dist: pre-commit; extra == 'dev'
Requires-Dist: pytest; extra == 'dev'
Requires-Dist: pytest-cov; extra == 'dev'
Requires-Dist: pytest-xdist; extra == 'dev'
Requires-Dist: pyyaml; extra == 'dev'
Requires-Dist: ruff; extra == 'dev'
Requires-Dist: sphinx; extra == 'dev'
Requires-Dist: sphinx-copybutton; extra == 'dev'
Requires-Dist: sphinx-rtd-theme; extra == 'dev'
Requires-Dist: sphinxcontrib-bibtex; extra == 'dev'
Requires-Dist: tox; extra == 'dev'
Provides-Extra: doc
Requires-Dist: furo; extra == 'doc'
Requires-Dist: jupyterlab; extra == 'doc'
Requires-Dist: myst-parser; extra == 'doc'
Requires-Dist: nbsphinx; extra == 'doc'
Requires-Dist: numpydoc; extra == 'doc'
Requires-Dist: sphinx; extra == 'doc'
Requires-Dist: sphinx-copybutton; extra == 'doc'
Requires-Dist: sphinx-rtd-theme; extra == 'doc'
Requires-Dist: sphinxcontrib-bibtex; extra == 'doc'
Provides-Extra: notebook
Requires-Dist: black[jupyter]<25.0.0,>=24.0.0; extra == 'notebook'
Requires-Dist: ipython; extra == 'notebook'
Requires-Dist: isort; extra == 'notebook'
Requires-Dist: jupyterlab; extra == 'notebook'
Requires-Dist: jupyterlab-code-formatter; extra == 'notebook'
Requires-Dist: jupyterlab-spellchecker; extra == 'notebook'
